camera_calibration/__init__.py
camera_calibration/camera_calibration.py
TH_camera_calibration-0.4.10.dist-info/METADATA
TH_camera_calibration-0.4.10.dist-info/WHEEL
TH_camera_calibration-0.4.10.dist-info/top_level.txt
TH_camera_calibration-0.4.10.dist-info/RECORD
